{"judul":"My Insanely Competent Underlings","slug":"my-insanely-competent-underlings","tipe":"Manhwa","released":"November 18, 2022","rating":"7.00","author":"Ban-in Ban-gyoÂ [Add, ]NoCountÂ [Add, ]","artist":"","status":"Ongoing","genre":["Action","Adventure","Drama","Fantasy","Shounen"],"synopsis":"Kedalaman labirin yang mengarah ke neraka di mana tidak mungkin untuk mundur. Gamer, yang masuk jajaran pahlawan, dan bahkan mereka yang disebut sebagai kekuatan absolut dari satu generasi gagal membersihkan zona dalam. “Kecuali keajaiban terjadi, kalian semua akan mati. Apakah kamu siap untuk mati?” Anggota timku menjawab dengan wajah tegas. “Tidak.” “Tidak.” “Tidak.” … Tidak ada?! Kebangkitan Hoyeon ke puncak dengan rekan setimnya yang sangat kompeten—atau gila—dalam game fantasi dimulai sekarang.","thumbnail":"https://kiryuu02.com/wp-content/uploads/2022/11/my-insanely-competent-underlings-590743-QeEFFzLz.webp"}