{"judul":"King Of Drama","slug":"king-of-drama","tipe":"Manhwa","released":"September 24, 2021","rating":"7","author":"Gobyeol","artist":"","status":"Ongoing","genre":["Comedy","Drama","Fantasy","Shounen","Slice of Life"],"synopsis":"“Jika saja aku terlahir kembali, aku ingin membuat sebuah drama gila yang spektakuler.” Tepat sebelum aku mati, aku memiliki sebuah harapan yang terlintas di benakku begitu saja layaknya sebuah kilat, dan sebuah “Sistem” yang tak diketahui menerima harapan aneh tersebut. Lee Hyunseok kembali ke saat dia masih menjadi seorang Sutradara (PD-Nim) untuk menciptakan sebuah drama gila yang spektakuler. Hantu yang juga merupakan master director, dan Iseol, aktris yang sedang naik daun, serta produser dari “Drama Gila” yang membahayakan nyawa Hyunseok, bertujuan untuk menyelesaikannya di akhir tahun. Mereka semua menjadi semakin dan semakin terkenal di seluruh dunia!","thumbnail":"https://kiryuu02.com/wp-content/uploads/2021/09/king-of-drama-773605-KJ14Z829-207x300.jpg"}