{"judul":"Emperor Hunt","slug":"emperor-hunt","tipe":"Manhwa","released":"Oktober 6, 2022","rating":"7.00","author":"KAN (IV)","artist":"","status":"Ongoing","genre":["Action","Adventure","Fantasy"],"synopsis":"Bumi dihancurkan. Kecuali ‘Yunsle’ yang abadi.\r\n Orang yang memusnahkan duniaku adalah yang terkuat di dunia ini? Aku tidak tahu dan aku akan membunuhmu sekali.\r\n Kepala berputar? Cepat. Tindakan? Sehat.\r\n Karakter .. Ini sedikit kasar tapi menghangatkan hati dan drama balas dendam fantasi konsep barunya dimulai!\r\n Hadiah Utama Kedua Kompetisi Ground Maximum 2021!","thumbnail":"https://kiryuu02.com/wp-content/uploads/2022/10/emperor-hunt-710922-XdO4OqsL-218x300.jpg"}