{"judul":"Apocalyptic Chef Awakening","slug":"apocalyptic-chef-awakening","rating":"7.6","Status":"Ongoing","Type":"Manhwa","Posted By":"Danzell","Posted On":"November 11, 2023","Updated On":"Oktober 8, 2025","Views":"?","genre":["Action","Adventure","Cooking","Fantasy"],"synopsis":"Shin Young-jun, seorang sersan koki, disambut oleh kiamat hanya beberapa hari sebelum liburan. Batalyon tersebut berubah menjadi kekacauan dalam sekejap, dan jaringan komunikasi terputus. Lalu sesuatu muncul di depan matanya! [Selamat atas kebangkitanmu!] [Pekerjaan: Koki Pemula Lv.1] Jika aku seorang pejuang atau pembunuh, aku akan mencoba untuk berdiri sendiri… Yang ditugaskan padanya adalah koki, yang jelas merupakan pekerjaan pendukung . Tidak ada yang bisa dilakukan jika sudah seperti ini. “Mulai sekarang, aku akan memberimu makan.”","thumbnail":"https://kiryuu02.com/wp-content/uploads/2023/11/aca523423423-e1699703771255-047315-iOs5i4Gn-jpg.webp"}