{"judul":"Reality Quest","slug":"reality-quest","tipe":"Manhwa","released":"Oktober 28, 2021","rating":"7","author":"Lee Joo-woon","artist":"","status":"Ongoing","genre":["Action","Drama","Fantasy","School Life","Shounen"],"synopsis":"Karena ancaman pengganggu sekolah untuk memberinya item game, Ha Do-wan, shuttle game yang tidak beruntung, meninggal setelah bermain game sepanjang malam selama seminggu. Saat dia meninggal, dia dibangkitkan kembali ke ruang kelas satu minggu sebelum dia meninggal… Semuanya sama seperti hari itu. Satu-satunya hal yang berubah adalah mengambang di depannya! Apa? Gunakan keterampilan permainan yang saya mainkan sejauh ini untuk mengalahkan pengganggu?!?!","thumbnail":"https://kiryuu02.com/wp-content/uploads/2021/10/reality-quest-243780-0HFMve0X-207x300.jpg"}