{"judul":"Demonic Master of Mount Kunlun","slug":"demonic-master-of-mount-kunlun","tipe":"Manhwa","released":"September 1, 2022","rating":"7.00","author":"Geulbyeol Jali, Heron Nest (Author), Wooyoo Saseon (Artist)","artist":"","status":"Ongoing","genre":["Action","Drama","Fantasy","Historical","Martial Arts","Shounen"],"synopsis":"Iblis Surgawi Sejati menjabat sebagai pemimpin muda Sekte Setan selama 100 tahun karena ayahnya, pemimpin Sekte itu, berumur panjang.\r\n Namun, setelah mewarisi posisi Pemimpin Kultus, yang tidak dia inginkan, dia meninggal hanya dalam satu tahun.\r\n Tetapi ketika dia bangun, dia sekarang masih bayi!\r\n Dia ditinggalkan di pinggir jalan, tetapi dia dijemput oleh seorang Taois dari Kunlun, sebuah sekte milik faksi keadilan.\r\n Saat itulah ia menjadi Jung Gwang, murid termuda dari Jeong Jabae.\r\n Saat dia meninggal karena sebab alami, dia tidak memiliki dendam.\r\n Dia lebih ingin tahu tentang kehidupan dengan hubungan yang hangat di antara orang-orang daripada yang berdarah.\r\n Dia tidak bisa menikmati kehidupan sebelumnya karena dia sibuk membersihkan kekacauan ayahnya, jadi bukankah dia harus hidup untuk dirinya sendiri kali ini?\r\n Tapi dia sekarang anak-anak. Setelah memasuki Kunlun, dia setidaknya harus memastikan dia tidak akan menyesal sebelum saat-saat terakhir.\r\n Di bawah pengaruhnya, Kunlun secara bertahap berubah.\r\n Taoisme? Itu bukan urusanku.\r\n Cara iblis? Aku sedikit muak.\r\n Kisah kehidupan yang bergejolak di Murim dari Iblis Surgawi Sejati yang terlahir kembali.","thumbnail":"https://kiryuu02.com/wp-content/uploads/2022/09/demonic-master-of-mount-kunlun-956255-z374Vp38-220x300.webp"}