{"judul":"Genius Prismatic Mage","slug":"genius-prismatic-mage","rating":"7.6","Status":"Ongoing","Type":"Manhwa","Released":"2025","Posted By":"Gans","Posted On":"April 10, 2025","Updated On":"Oktober 13, 2025","Views":"?","genre":[],"synopsis":"Di daerah kumuh hiduplah seorang anak laki-laki bernama Ray yang kurang emosi. Dia tiba-tiba memperoleh kemampuan untuk melihat “warna” yang tidak dapat dilihat orang lain, dan dia memiliki kekuatan untuk mengendalikannya. Suatu hari, dia kehilangan tempat berlindung, jalan bawah tanah, dan teman-temannya karena seorang penyihir. Dia bahkan kehilangan Niles, yang selama ini dia percayai dan ikuti. Bocah tanpa emosi itu bersumpah akan membalas dendam, memulai pencariannya untuk mendapatkan kembali emosinya.","thumbnail":"https://kiryuu02.com/wp-content/uploads/2025/04/genius-prismatic-mage-167455-pI5w9Ffn.webp"}