{"judul":"Reborn on the Demonic Cult Battlefield","slug":"reborn-on-the-demonic-cult-battlefield","rating":"7.6","Status":"Ongoing","Type":"Manhwa","Released":"2025","Author":"New Sword Day, Winter Bandit","Posted By":"Gans","Posted On":"September 10, 2025","Updated On":"Oktober 17, 2025","Views":"?","genre":["Action","Fantasy","Martial Arts","Shounen"],"synopsis":"Dulu aib klan, sekarang master memori dengan kemampuan bela diri tingkat maksimal?! Mati hidup kembali, kembali ke garis depan, kali ini aku benar-benar bukan babi!","thumbnail":"https://kiryuu02.com/wp-content/uploads/2025/09/reborn-on-the-demonic-cult-battlefield-110828-7s0RGhdl.png"}