{"judul":"The Silent Warrior","slug":"the-silent-warrior","tipe":"Manhwa","released":"Juli 27, 2024","rating":"7.00","author":"A-Nomad, Road Warrior, Team Matgamari (Author), Kim Hak-Young & Team Matgamari (Artist)","artist":"","status":"Ongoing","genre":["Action","Adventure","Drama","Fantasy","Martial Arts","Shounen"],"synopsis":"“Hadapilah takdirmu.” Di dunia alternatif yang disebut Otherworld—dipenuhi dengan makhluk-makhluk dan bencana-bencana Bumi—seorang pejuang kuno, seorang manusia yang dipanggil sejak lama ke dalam dunia tersebut, bertekad untuk mengakhiri semuanya. Didorong oleh kebencian dari masa lalu yang tidak diketahui, perjalanan ini mengungkap identitas tersembunyi, menjalankan misi rahasia, menghadapi ujian kematian, menavigasi melalui pengkhianatan, dan melewati pertumpahan darah. Apa yang disembunyikan bayang-bayang, dan takdir apa yang menunggu di jantung yang tidak diketahui?","thumbnail":"https://kiryuu02.com/wp-content/uploads/2024/07/the-silent-warrior-199854-9A4Z1r33.jpg"}