{"judul":"The Scout’s Dream","slug":"the-scout-s-dream","rating":"7.6","Status":"Ongoing","Type":"Manhwa","Released":"2025","Author":"Woollee","Posted By":"Gans","Posted On":"Oktober 4, 2025","Updated On":"Oktober 5, 2025","Views":"?","genre":["Drama","Fantasy","Shounen","Sports"],"synopsis":"Aku, mantan pemain sepak bola, kembali ke 10 tahun yang lalu. “Sekarang aku tahu siapa yang akan menjadi bintang sepak bola. Aku akan mencari permata tersembunyi dan membangun tim terbaik! Drama olahraga tentang rekrutmen pemain yang lebih menegangkan daripada pertandingan itu sendiri.","thumbnail":"https://kiryuu02.com/wp-content/uploads/2025/10/the-scouts-dream-171053-B8rsUXAm.jpg"}