{"judul":"Nano Machine","slug":"nano-machine","rating":"7.6","Status":"Ongoing","Type":"Manhwa","Released":"2020","Author":"Han-Joong-Wueol-Ya","Artist":"Guem-Gang-Bul-Gae","Posted By":"Gans","Posted On":"November 13, 2024","Updated On":"Oktober 16, 2025","Views":"?","genre":["Action","Adventure","Fantasy","Martial Arts","Wuxia"],"synopsis":"Setelah direndahkan dan menghabiskan hidupnya dalam bahaya, seorang yatim piatu dari pemuja iblis, Yeo-Woon, mendapatkan kunjungan tak terduga dari keturunannya dari masa depan yang memasukkan sebuah mesin nano ke dalam tubuh Cheon-Woon, yang mengubah hidup Cheon Yeo Woon setelah aktivasi. Ikuti Cerita tentang perjalanan Cheon Yeo-Woon di komikcast.com, melewati pemujaan setan dan naik menjadi yang ahli beladiri terbaik baru saja dimulai.","thumbnail":"https://kiryuu02.com/wp-content/uploads/2021/03/vol-2-766x1024-241277-OCDAuWmC.jpg"}