{"judul":"Return of the Elemental Lord","slug":"return-of-the-elemental-lord","tipe":"Manhwa","released":"Februari 28, 2023","rating":"7.00","author":"Sangyoung Seong (Author), Seungbeom Park (Artist)","artist":"","status":"Ongoing","genre":["Action","Adventure","Fantasy","Shounen"],"synopsis":"Ini adalah kisah tentang raja roh unsur yang bereinkarnasi sebagai manusia. Bawahannya, roh unsur, telah menemukannya di dunia manusia dan mencoba membantunya mengingat kehidupan sebelumnya. Novel dengan judul yang sama ditulis oleh Sangyoung Seong, penulis webtoon The Gamer dan Wizardly Tower. Ditulis dan diilustrasikan oleh Seungbeom Park, penulis webtoon Wizardly Tower.","thumbnail":"https://kiryuu02.com/wp-content/uploads/2023/02/return-of-the-elemental-lord-021800-TSzyF3aC-222x300.jpg"}