{"judul":"This Girl is a Little Wild","slug":"this-girl-is-a-little-wild","tipe":"Manhwa","released":"Maret 16, 2021","rating":"8.5","author":"303 Planet","artist":"","status":"Ongoing","genre":["Action","Comedy","Fantasy","Romance","Shoujo"],"synopsis":"Saat dia dikalahkan, Raja Iblis menggunakan kekuatan terakhirnya untuk mengutuk Sir Roel, kapten legendaris Ksatria Suci, ke dalam tubuh seorang gadis yang lemah. Roel – seorang wanita sejak awal! – lelah dengan kehidupan sebelumnya dan tidak dapat kembali ke tubuh aslinya, memutuskan untuk menjalani kehidupan mewah sebagai Sila Epheria, putri bangsawan yang jiwanya tertukar dengan miliknya. Segala sesuatunya tidak berjalan sesuai rencana ketika keluarga barunya menempatkan dirinya dalam bahaya, memaksanya untuk menemukan cara untuk membuktikan jati dirinya … Akankah Roel / Sila dapat menjalani kehidupan yang tenang sesuai keinginannya? Atau adakah sesuatu yang lebih dari kehidupan baru yang dia terima?","thumbnail":"https://kiryuu02.com/wp-content/uploads/2021/03/this-girl-is-a-little-wild-222815-p599DOuA-222x300.jpeg"}