{"judul":"Match Made in Heaven by Chance","slug":"match-made-in-heaven-by-chance","tipe":"Manhwa","released":"Februari 20, 2022","rating":"7.00","author":"Honey Skein","artist":"","status":"Ongoing","genre":["Comedy","Drama","Josei","Romance"],"synopsis":"‘Sudah berapa lama aku berbaring di rumah…?’ Han Jia, yang tahun ini berusia 32 tahun (dia adalah seorang pekerja lepas yang masih belum memiliki pekerjaan tetap/pengangguran), menderita karena tekanan yang diberikan oleh orang-orang di sekitar. dia yang terus menyuruhnya untuk menikah. Sekitar waktu yang sama, Jin Mincheol, teman masa kecilnya yang datang ke kampung halaman Jia untuk liburan, mengalami masalah yang sama. Kemudian, kedua orang itu menikah begitu saja. Sekarang mereka sudah menikah….. ‘Hah? Kami cocok satu sama lain lebih dari yang kukira?’","thumbnail":"https://kiryuu02.com/wp-content/uploads/2022/02/match-made-in-heaven-by-chance-942360-QGcw1FPC.jpg"}