{"judul":"Would You Like to Sign The Contract?","slug":"would-you-like-to-sign-the-contract","tipe":"Manhwa","released":"September 16, 2023","rating":"7.00","author":"-","artist":"","status":"Ongoing","genre":["Action"],"synopsis":"“Ini demi Presdir. Apa ada masalah?” Kata-kata ini kembali bagaikan pisau, dan pada hari itu, aku mati. Lalu, aku hidup kembali. Dari Yunseok., yang merupakan direktur dari perusahaan investasi real estate terbaik di Korea Selatan, menjadi Kim Donggyu, seorang penyendiri dan pecundang. Setelah frustasi sesaat, aku bangkit kembali untuk balas dendam. Tunggu aku. Aku pasti akan membuat mereka membayar atas apa yang telah mereka perbuat padaku. Hari ini, aku membuat rencana sebagai Yunseok dan menjalankannya sebagai Kim Donggyu. Demi balas dendam kami.","thumbnail":"https://kiryuu02.com/wp-content/uploads/2023/09/would-you-like-to-sign-the-contract-139798-tOzQFqYa-210x300.webp"}