{"judul":"To Not Die","slug":"to-not-die","tipe":"Manhwa","released":"Juni 25, 2021","rating":"7.4","author":"Parae","artist":"","status":"Ongoing","genre":["Action","Adventure","Drama","Martial Arts","Psychological","School Life"],"synopsis":"Aku Dajun adalah siswa SMA yang setiap hari di-bully di sekolah. Dia menemukan sebuah wawancara di TV tepat ketika dia hampir menyerah pada kehidupan. Itu dengan seorang pembunuh yang membunuh teman-teman sekelas yang menggertaknya. Dajun menjadi terinspirasi oleh apa yang dia lihat dan memutuskan untuk membalas dendam juga.","thumbnail":"https://kiryuu02.com/wp-content/uploads/2021/06/to-not-die-649593-xzpeHItc.png"}