{"judul":"Troll Trap","slug":"troll-trap","tipe":"Manhwa","released":"Maret 16, 2021","rating":"7.5","author":"LEE Won-Seek","artist":"","status":"Ongoing","genre":["Action","Fantasy","School Life"],"synopsis":"Pernahkah Anda memperhatikan bahwa seseorang yang Anda kenal tidak lagi menjadi diri mereka sendiri? Perubahan halus yang mereka tunjukkan yang menunjukkan bahwa mereka bukan lagi… manusia? Bergabunglah dengan pemburu Ha-Te, Sul-bak, dan rekan paruh waktu mereka Ji-Hyun Kang dalam petualangan berburu troll untuk menyelamatkan umat manusia!","thumbnail":"https://kiryuu02.com/wp-content/uploads/2021/03/troll-trap-405511-Z5MQ6QDu-207x300.jpg"}