{"judul":"Player Who Returned 10,000 Years Later","slug":"player-who-returned-10-000-years-later","rating":"7.6","Status":"Ongoing","Type":"Manhwa","Released":"2022","Author":"Butterfly Valley Joo Kyung Maeng [Add, ]","Artist":"4PLAYER (COPIN)","Serialization":"KakaoPage (KakaoPage)Kakao Webtoon (Daum)","Posted By":"kiryuu","Posted On":"November 11, 2024","Updated On":"Oktober 13, 2025","Views":"?","genre":["Action","Adventure","Comedy","Demon","Drama","Fantasy","Seinen"],"synopsis":"Suatu hari, Kang Woo tiba-tiba jatuh ke neraka, dan yang dia miliki hanyalah keinginan bertahan hidup yang kuat dan skill predator. Dari neraka tingkat ke-1 hingga ke-9, dia menelan ratusan ribu demon, sampai-sampai 7 Archduke akhirnya tunduk padanya. “Master, kenapa kau ingin kembali? Bukankah kau telah memiliki semua yang ada di neraka?” “Tepatnya apa yang aku miliki?” Tidak ada yang bisa dimakan ataupun sesuatu yang menghibur! Hanya tanah tandus dan demon mengerikan yang memenuhi neraka. “Aku akan pulang.” Setelah 10.000 tahun di 9 neraka, dia akhirnya kembali ke Bumi.","thumbnail":"https://kiryuu02.com/wp-content/uploads/2022/08/player-who-returned-10000-years-later-865525-x94qXr1P.webp"}