{"judul":"Metro Hunter","slug":"metro-hunter","tipe":"Manhwa","released":"Agustus 11, 2021","rating":"7","author":"LEE Doo Yeop","artist":"","status":"Ongoing","genre":["Action","Adventure","Fantasy","Sci-fi"],"synopsis":"The capital of Korea, Seoul. All over the subway Monsters of unknown origin started appearing. But don’t worry, because In this nightmare-like crisis, there are saviors who will protect you. We call them the Metro Hunters!","thumbnail":"https://kiryuu02.com/wp-content/uploads/2021/08/metro-hunter-982525-mp7aS5U8.jpg"}