{"judul":"XO Sisters","slug":"xo-sisters","tipe":"Manhwa","released":"Maret 13, 2021","rating":"7.6","author":"Park Seong-Su","artist":"","status":"Completed","genre":["Action","Comedy","Harem","Martial Arts","Romance","School Life","Shounen","Supernatural"],"synopsis":"Protagonis kita Jo Cheul-Hee adalah anak nakal yang suka berkelahi dan bertujuan untuk mengendalikan sekolah barunya tempat dia dipindahkan, tetapi yang tidak dia ketahui adalah bahwa itu adalah sekolah khusus perempuan. Menjadi satu-satunya siswa laki-laki di sana, semua orang mengira dia gay!","thumbnail":"https://kiryuu02.com/wp-content/uploads/2021/03/xo-sisters-223023-T2kwpN7I-207x300.jpg"}